README.md
setup.py
matplotlib_helper/__init__.py
matplotlib_helper/colors.py
matplotlib_helper/publish.py
matplotlib_helper.egg-info/PKG-INFO
matplotlib_helper.egg-info/SOURCES.txt
matplotlib_helper.egg-info/dependency_links.txt
matplotlib_helper.egg-info/requires.txt
matplotlib_helper.egg-info/top_level.txt