Metadata-Version: 1.0
Name: matplotlib-helper
Version: 1.0
Summary: Module for helping and plotting in matplotlib
Home-page: UNKNOWN
Author: Santosh Kumar Radha
Author-email: srr70@case.edu
License: UNKNOWN
Platform: UNKNOWN
